pygeos/_geometry.cpython-311-darwin.so
pygeos/predicates.py
pygeos/creation.py
pygeos/strtree.py
pygeos/_version.py
pygeos/_geos.cpython-311-darwin.so
pygeos/linear.py
pygeos/io.py
pygeos/measurement.py
pygeos/__init__.py
pygeos/_geos.pxd
pygeos/_geos.pyx
pygeos/set_operations.py
pygeos/lib.cpython-311-darwin.so
pygeos/geometry.py
pygeos/_geometry.pyx
pygeos/_pygeos_api.pxd
pygeos/enum.py
pygeos/testing.py
pygeos/constructive.py
pygeos/coordinates.py
pygeos/decorators.py
pygeos/tests/test_constructive.py
pygeos/tests/test_strtree.py
pygeos/tests/test_misc.py
pygeos/tests/test_measurement.py
pygeos/tests/test_set_operations.py
pygeos/tests/__init__.py
pygeos/tests/test_io.py
pygeos/tests/test_creation.py
pygeos/tests/common.py
pygeos/tests/test_coordinates.py
pygeos/tests/test_predicates.py
pygeos/tests/test_linear.py
pygeos/tests/test_geometry.py
pygeos/tests/test_creation_indices.py
pygeos/tests/test_testing.py
pygeos/.dylibs/libgeos.3.10.4.dylib
pygeos/.dylibs/libgeos_c.1.16.2.dylib
pygeos-0.14.dist-info/RECORD
pygeos-0.14.dist-info/LICENSE
pygeos-0.14.dist-info/LICENSE_GEOS
pygeos-0.14.dist-info/WHEEL
pygeos-0.14.dist-info/top_level.txt
pygeos-0.14.dist-info/METADATA
