Metadata-Version: 2.1
Name: pygeos
Version: 0.14
Summary: GEOS wrapped in numpy ufuncs
Home-page: https://github.com/pygeos/pygeos
Author: Casper van der Wel
Author-email: caspervdw@gmail.com
License: BSD 3-Clause
Classifier: Programming Language :: Python :: 3
Classifier: Intended Audience :: Science/Research
Classifier: Intended Audience :: Developers
Classifier: Development Status :: 4 - Beta
Classifier: Topic :: Scientific/Engineering
Classifier: Topic :: Software Development
Classifier: Operating System :: Unix
Classifier: Operating System :: MacOS
Classifier: Operating System :: Microsoft :: Windows
Requires-Python: >=3.7
License-File: LICENSE
License-File: LICENSE_GEOS
License-File: LICENSE_win32
Requires-Dist: numpy (>=1.13)
Provides-Extra: docs
Requires-Dist: sphinx ; extra == 'docs'
Requires-Dist: numpydoc ; extra == 'docs'
Provides-Extra: test
Requires-Dist: pytest ; extra == 'test'
